{
    "welcome": {
        "embed": {
            "author": {
            "name": "Hi, Zerobot here!"
            },
            "thumbnail": {
                "url": "https://cdn.discordapp.com/attachments/433413771982012421/434490807303667713/zeroToMasteryIcon.png"
            },
            "description": 
            "Welcome to the the Zero to Mastery discord server, I am here to help with any questions you may have. Type ```-help``` into the chat box below for a list of topics I can help you with",
            "color": 2743241

        }
    }
}